CHANGES.txt
MANIFEST.in
README
setup.py
shogen2.py
shogen2.egg-info/PKG-INFO
shogen2.egg-info/SOURCES.txt
shogen2.egg-info/dependency_links.txt
shogen2.egg-info/requires.txt
shogen2.egg-info/top_level.txt
src/__init__.py
src/query.py
src/sbml.py
src/utils.py
src/encodings/filter_couples.lp
src/encodings/sgs.lp