Metadata-Version: 1.0
Name: shogen2
Version: 1.1.1
Summary: Finding shortest genome segments that regulate metabolic pathways
Home-page: http://pypi.python.org/pypi/shogen2/
Author: Sven Thiele
Author-email: sthiele78@gmail.com
License: GPLv3+
Platform: UNKNOWN
